zzignal-0.1.20.dist-info/METADATA
zzignal-0.1.20.dist-info/WHEEL
zzignal-0.1.20.dist-info/licenses/LICENSE
zzignal/__init__.py
zzignal/zzignal.cpython-312-x86_64-linux-gnu.so
zzignal-0.1.20.dist-info/RECORD
